pyminicircuits/__init__.py
pyminicircuits/cmd/__init__.py
pyminicircuits/cmd/attenuator.py
pyminicircuits/cmd/powersensor.py
pyminicircuits-0.0.1.dev0.dist-info/METADATA
pyminicircuits-0.0.1.dev0.dist-info/RECORD
pyminicircuits-0.0.1.dev0.dist-info/WHEEL
pyminicircuits-0.0.1.dev0.dist-info/entry_points.txt
pyminicircuits-0.0.1.dev0.dist-info/top_level.txt
